{
  "firstLayout": "",
  "gdVersion": {
    "build": 217,
    "major": 5,
    "minor": 4,
    "revision": 0
  },
  "properties": {
    "adaptGameResolutionAtRuntime": true,
    "antialiasingMode": "MSAA",
    "antialisingEnabledOnMobile": false,
    "folderProject": true,
    "orientation": "default",
    "packageName": "com.example.gamename",
    "pixelsRounding": false,
    "projectUuid": "02663f46-ccd6-42ae-b620-190651ba0a8a",
    "scaleMode": "linear",
    "sizeOnStartupMode": "adaptWidth",
    "templateSlug": "",
    "useExternalSourceFiles": false,
    "version": "1.0.0",
    "name": "Graphical Game",
    "description": "",
    "author": "",
    "windowWidth": 1920,
    "windowHeight": 1080,
    "latestCompilationDirectory": "",
    "maxFPS": 60,
    "minFPS": 20,
    "verticalSync": false,
    "platformSpecificAssets": {},
    "loadingScreen": {
      "backgroundColor": 0,
      "backgroundFadeInDuration": 0.2,
      "backgroundImageResourceName": "",
      "gdevelopLogoStyle": "light",
      "logoAndProgressFadeInDuration": 0.2,
      "logoAndProgressLogoFadeInDelay": 0,
      "minDuration": 1.5,
      "progressBarColor": 16777215,
      "progressBarHeight": 20,
      "progressBarMaxWidth": 200,
      "progressBarMinWidth": 40,
      "progressBarWidthPercent": 30,
      "showGDevelopSplash": true,
      "showProgressBar": true
    },
    "watermark": {
      "placement": "bottom-left",
      "showWatermark": true
    },
    "authorIds": [],
    "authorUsernames": [],
    "categories": [],
    "playableDevices": [],
    "extensionProperties": [],
    "platforms": [
      {
        "name": "GDevelop JS platform"
      }
    ],
    "currentPlatform": "GDevelop JS platform"
  },
  "resources": {
    "resources": [
      {
        "alwaysLoaded": false,
        "file": "pixel-art-cute-black-cat-cartoon-character-2-png.webp",
        "kind": "image",
        "metadata": "",
        "name": "pixel-art-cute-black-cat-cartoon-character-2-png.webp",
        "smoothed": true,
        "userAdded": false
      },
      {
        "alwaysLoaded": false,
        "file": "assets/monochrome_tilemap_transparent_packed.png",
        "kind": "image",
        "metadata": "",
        "name": "monochrome_tilemap_transparent_packed.png",
        "smoothed": false,
        "userAdded": true,
        "origin": {
          "identifier": "https://asset-resources.gdevelop.io/public-resources/Kenney Tilemaps/Pixel Art/7da13c10c28bc5ec3e8ceed7c1b980cf019b26e4a5ea7bba589be1b248f06b85_monochrome_tilemap_transparent_packed.png",
          "name": "monochrome_tilemap_transparent_packed.png"
        }
      },
      {
        "alwaysLoaded": false,
        "file": "R (1).png",
        "kind": "image",
        "metadata": "",
        "name": "R (1).png",
        "smoothed": true,
        "userAdded": false
      },
      {
        "alwaysLoaded": false,
        "file": "Cat-2-Idle.png",
        "kind": "image",
        "metadata": "",
        "name": "Cat-2-Idle.png",
        "smoothed": true,
        "userAdded": false
      },
      {
        "alwaysLoaded": false,
        "file": "row-1-column-1.png",
        "kind": "image",
        "metadata": "",
        "name": "row-1-column-1.png",
        "smoothed": true,
        "userAdded": false
      },
      {
        "alwaysLoaded": false,
        "file": "row-1-column-2.png",
        "kind": "image",
        "metadata": "",
        "name": "row-1-column-2.png",
        "smoothed": true,
        "userAdded": false
      },
      {
        "alwaysLoaded": false,
        "file": "row-1-column-3.png",
        "kind": "image",
        "metadata": "",
        "name": "row-1-column-3.png",
        "smoothed": true,
        "userAdded": false
      },
      {
        "alwaysLoaded": false,
        "file": "row-1-column-4.png",
        "kind": "image",
        "metadata": "",
        "name": "row-1-column-4.png",
        "smoothed": true,
        "userAdded": false
      },
      {
        "alwaysLoaded": false,
        "file": "row-1-column-5.png",
        "kind": "image",
        "metadata": "",
        "name": "row-1-column-5.png",
        "smoothed": true,
        "userAdded": false
      },
      {
        "alwaysLoaded": false,
        "file": "row-1-column-6.png",
        "kind": "image",
        "metadata": "",
        "name": "row-1-column-6.png",
        "smoothed": true,
        "userAdded": false
      },
      {
        "alwaysLoaded": false,
        "file": "row-1-column-7.png",
        "kind": "image",
        "metadata": "",
        "name": "row-1-column-7.png",
        "smoothed": true,
        "userAdded": false
      },
      {
        "alwaysLoaded": false,
        "file": "row-1-column-8.png",
        "kind": "image",
        "metadata": "",
        "name": "row-1-column-8.png",
        "smoothed": true,
        "userAdded": false
      },
      {
        "alwaysLoaded": false,
        "file": "row-1-column-9.png",
        "kind": "image",
        "metadata": "",
        "name": "row-1-column-9.png",
        "smoothed": true,
        "userAdded": false
      },
      {
        "alwaysLoaded": false,
        "file": "row-1-column-10.png",
        "kind": "image",
        "metadata": "",
        "name": "row-1-column-10.png",
        "smoothed": true,
        "userAdded": false
      },
      {
        "alwaysLoaded": false,
        "file": "row-1-column0.png",
        "kind": "image",
        "metadata": "",
        "name": "row-1-column0.png",
        "smoothed": true,
        "userAdded": false
      },
      {
        "alwaysLoaded": false,
        "file": "row-1-column1.png",
        "kind": "image",
        "metadata": "",
        "name": "row-1-column1.png",
        "smoothed": true,
        "userAdded": false
      },
      {
        "alwaysLoaded": false,
        "file": "row-1-column2.png",
        "kind": "image",
        "metadata": "",
        "name": "row-1-column2.png",
        "smoothed": true,
        "userAdded": false
      },
      {
        "alwaysLoaded": false,
        "file": "row-1-column3.png",
        "kind": "image",
        "metadata": "",
        "name": "row-1-column3.png",
        "smoothed": true,
        "userAdded": false
      },
      {
        "alwaysLoaded": false,
        "file": "row-1-column4.png",
        "kind": "image",
        "metadata": "",
        "name": "row-1-column4.png",
        "smoothed": true,
        "userAdded": false
      },
      {
        "alwaysLoaded": false,
        "file": "row-1-column5.png",
        "kind": "image",
        "metadata": "",
        "name": "row-1-column5.png",
        "smoothed": true,
        "userAdded": false
      },
      {
        "alwaysLoaded": false,
        "file": "row-1-column6.png",
        "kind": "image",
        "metadata": "",
        "name": "row-1-column6.png",
        "smoothed": true,
        "userAdded": false
      },
      {
        "alwaysLoaded": false,
        "file": "row-1-column7.png",
        "kind": "image",
        "metadata": "",
        "name": "row-1-column7.png",
        "smoothed": true,
        "userAdded": false
      },
      {
        "alwaysLoaded": false,
        "file": "row-1-column8.png",
        "kind": "image",
        "metadata": "",
        "name": "row-1-column8.png",
        "smoothed": true,
        "userAdded": false
      },
      {
        "alwaysLoaded": false,
        "file": "row-1-column9.png",
        "kind": "image",
        "metadata": "",
        "name": "row-1-column9.png",
        "smoothed": true,
        "userAdded": false
      },
      {
        "alwaysLoaded": false,
        "file": "row-1-column10.png",
        "kind": "image",
        "metadata": "",
        "name": "row-1-column10.png",
        "smoothed": true,
        "userAdded": false
      },
      {
        "alwaysLoaded": false,
        "file": "row-1-column11.png",
        "kind": "image",
        "metadata": "",
        "name": "row-1-column11.png",
        "smoothed": true,
        "userAdded": false
      },
      {
        "alwaysLoaded": false,
        "file": "row-1-column12.png",
        "kind": "image",
        "metadata": "",
        "name": "row-1-column12.png",
        "smoothed": true,
        "userAdded": false
      },
      {
        "alwaysLoaded": false,
        "file": "row-1-column13.png",
        "kind": "image",
        "metadata": "",
        "name": "row-1-column13.png",
        "smoothed": true,
        "userAdded": false
      },
      {
        "alwaysLoaded": false,
        "file": "row-1-column14.png",
        "kind": "image",
        "metadata": "",
        "name": "row-1-column14.png",
        "smoothed": true,
        "userAdded": false
      },
      {
        "alwaysLoaded": false,
        "file": "row-1-column15.png",
        "kind": "image",
        "metadata": "",
        "name": "row-1-column15.png",
        "smoothed": true,
        "userAdded": false
      },
      {
        "alwaysLoaded": false,
        "file": "row-1-column16.png",
        "kind": "image",
        "metadata": "",
        "name": "row-1-column16.png",
        "smoothed": true,
        "userAdded": false
      },
      {
        "alwaysLoaded": false,
        "file": "../../../Downloads/PineTools.com_files 2/row-1-column-1.png",
        "kind": "image",
        "metadata": "",
        "name": "../../../Downloads/PineTools.com_files 2/row-1-column-1.png",
        "smoothed": true,
        "userAdded": false
      },
      {
        "alwaysLoaded": false,
        "file": "row-1-column17.png",
        "kind": "image",
        "metadata": "",
        "name": "row-1-column17.png",
        "smoothed": true,
        "userAdded": false
      },
      {
        "alwaysLoaded": false,
        "file": "row-1-column18.png",
        "kind": "image",
        "metadata": "",
        "name": "row-1-column18.png",
        "smoothed": true,
        "userAdded": false
      },
      {
        "alwaysLoaded": false,
        "file": "row-1-column19.png",
        "kind": "image",
        "metadata": "",
        "name": "row-1-column19.png",
        "smoothed": true,
        "userAdded": false
      },
      {
        "alwaysLoaded": false,
        "file": "row-1-column20.png",
        "kind": "image",
        "metadata": "",
        "name": "row-1-column20.png",
        "smoothed": true,
        "userAdded": false
      },
      {
        "alwaysLoaded": false,
        "file": "row-1-column21.png",
        "kind": "image",
        "metadata": "",
        "name": "row-1-column21.png",
        "smoothed": true,
        "userAdded": false
      },
      {
        "alwaysLoaded": false,
        "file": "row-1-column22.png",
        "kind": "image",
        "metadata": "",
        "name": "row-1-column22.png",
        "smoothed": true,
        "userAdded": false
      },
      {
        "alwaysLoaded": false,
        "file": "row-1-column23.png",
        "kind": "image",
        "metadata": "",
        "name": "row-1-column23.png",
        "smoothed": true,
        "userAdded": false
      },
      {
        "alwaysLoaded": false,
        "file": "row-1-column24.png",
        "kind": "image",
        "metadata": "",
        "name": "row-1-column24.png",
        "smoothed": true,
        "userAdded": false
      },
      {
        "alwaysLoaded": false,
        "file": "row-1-column25.png",
        "kind": "image",
        "metadata": "",
        "name": "row-1-column25.png",
        "smoothed": true,
        "userAdded": false
      },
      {
        "alwaysLoaded": false,
        "file": "row-1-column26.png",
        "kind": "image",
        "metadata": "",
        "name": "row-1-column26.png",
        "smoothed": true,
        "userAdded": false
      },
      {
        "alwaysLoaded": false,
        "file": "row-1-column-11.png",
        "kind": "image",
        "metadata": "",
        "name": "row-1-column-11.png",
        "smoothed": true,
        "userAdded": false
      },
      {
        "alwaysLoaded": false,
        "file": "row-1-column-12.png",
        "kind": "image",
        "metadata": "",
        "name": "row-1-column-12.png",
        "smoothed": true,
        "userAdded": false
      },
      {
        "alwaysLoaded": false,
        "file": "row-1-column-13.png",
        "kind": "image",
        "metadata": "",
        "name": "row-1-column-13.png",
        "smoothed": true,
        "userAdded": false
      },
      {
        "alwaysLoaded": false,
        "file": "row-1-column-14.png",
        "kind": "image",
        "metadata": "",
        "name": "row-1-column-14.png",
        "smoothed": true,
        "userAdded": false
      },
      {
        "alwaysLoaded": false,
        "file": "row-1-column27.png",
        "kind": "image",
        "metadata": "",
        "name": "row-1-column27.png",
        "smoothed": true,
        "userAdded": false
      },
      {
        "alwaysLoaded": false,
        "file": "row-1-column28.png",
        "kind": "image",
        "metadata": "",
        "name": "row-1-column28.png",
        "smoothed": true,
        "userAdded": false
      },
      {
        "alwaysLoaded": false,
        "file": "row-1-column29.png",
        "kind": "image",
        "metadata": "",
        "name": "row-1-column29.png",
        "smoothed": true,
        "userAdded": false
      },
      {
        "alwaysLoaded": false,
        "file": "row-1-column30.png",
        "kind": "image",
        "metadata": "",
        "name": "row-1-column30.png",
        "smoothed": true,
        "userAdded": false
      },
      {
        "alwaysLoaded": false,
        "file": "row-1-column31.png",
        "kind": "image",
        "metadata": "",
        "name": "row-1-column31.png",
        "smoothed": true,
        "userAdded": false
      },
      {
        "alwaysLoaded": false,
        "file": "row-1-column32.png",
        "kind": "image",
        "metadata": "",
        "name": "row-1-column32.png",
        "smoothed": true,
        "userAdded": false
      },
      {
        "alwaysLoaded": false,
        "file": "row-1-column33.png",
        "kind": "image",
        "metadata": "",
        "name": "row-1-column33.png",
        "smoothed": true,
        "userAdded": false
      },
      {
        "alwaysLoaded": false,
        "file": "row-1-column34.png",
        "kind": "image",
        "metadata": "",
        "name": "row-1-column34.png",
        "smoothed": true,
        "userAdded": false
      },
      {
        "alwaysLoaded": false,
        "file": "row-1-column35.png",
        "kind": "image",
        "metadata": "",
        "name": "row-1-column35.png",
        "smoothed": true,
        "userAdded": false
      },
      {
        "alwaysLoaded": false,
        "file": "row-1-column36.png",
        "kind": "image",
        "metadata": "",
        "name": "row-1-column36.png",
        "smoothed": true,
        "userAdded": false
      },
      {
        "alwaysLoaded": false,
        "file": "row-1-column37.png",
        "kind": "image",
        "metadata": "",
        "name": "row-1-column37.png",
        "smoothed": true,
        "userAdded": false
      },
      {
        "alwaysLoaded": false,
        "file": "row-1-column38.png",
        "kind": "image",
        "metadata": "",
        "name": "row-1-column38.png",
        "smoothed": true,
        "userAdded": false
      },
      {
        "alwaysLoaded": false,
        "file": "row-1-column39.png",
        "kind": "image",
        "metadata": "",
        "name": "row-1-column39.png",
        "smoothed": true,
        "userAdded": false
      },
      {
        "alwaysLoaded": false,
        "file": "row-1-column40.png",
        "kind": "image",
        "metadata": "",
        "name": "row-1-column40.png",
        "smoothed": true,
        "userAdded": false
      },
      {
        "alwaysLoaded": false,
        "file": "row-1-column41.png",
        "kind": "image",
        "metadata": "",
        "name": "row-1-column41.png",
        "smoothed": true,
        "userAdded": false
      },
      {
        "alwaysLoaded": false,
        "file": "row-1-column42.png",
        "kind": "image",
        "metadata": "",
        "name": "row-1-column42.png",
        "smoothed": true,
        "userAdded": false
      },
      {
        "alwaysLoaded": false,
        "file": "row-1-column43.png",
        "kind": "image",
        "metadata": "",
        "name": "row-1-column43.png",
        "smoothed": true,
        "userAdded": false
      },
      {
        "alwaysLoaded": false,
        "file": "row-1-column44.png",
        "kind": "image",
        "metadata": "",
        "name": "row-1-column44.png",
        "smoothed": true,
        "userAdded": false
      },
      {
        "alwaysLoaded": false,
        "file": "row-1-column45.png",
        "kind": "image",
        "metadata": "",
        "name": "row-1-column45.png",
        "smoothed": true,
        "userAdded": false
      }
    ],
    "resourceFolders": []
  },
  "objects": [],
  "objectsFolderStructure": {
    "folderName": "__ROOT"
  },
  "objectsGroups": [],
  "variables": [],
  "layouts": [
    {
      "__REFERENCE_TO_SPLIT_OBJECT": true,
      "referenceTo": "/layouts/untitled-scene"
    }
  ],
  "externalEvents": [],
  "eventsFunctionsExtensions": [],
  "externalLayouts": [],
  "externalSourceFiles": []
}